{
    "path": "images/game/ball_4_cb_multipliers.png",
    "frame_size": {
        "x": 29,
        "y": 29
    },
    "states": [
        {
            "pos": {
                "x": 0,
                "y": 0
            },
            "frames": {
                "x": 1,
                "y": 1
            }
        },
        {
            "pos": {
                "x": 29,
                "y": 0
            },
            "frames": {
                "x": 1,
                "y": 1
            }
        },
        {
            "pos": {
                "x": 58,
                "y": 0
            },
            "frames": {
                "x": 1,
                "y": 1
            }
        },
        {
            "pos": {
                "x": 87,
                "y": 0
            },
            "frames": {
                "x": 1,
                "y": 1
            }
        },
        {
            "pos": {
                "x": 116,
                "y": 0
            },
            "frames": {
                "x": 1,
                "y": 1
            }
        },
        {
            "pos": {
                "x": 145,
                "y": 0
            },
            "frames": {
                "x": 1,
                "y": 1
            }
        },
        {
            "pos": {
                "x": 174,
                "y": 0
            },
            "frames": {
                "x": 1,
                "y": 1
            }
        },
        {
            "pos": {
                "x": 203,
                "y": 0
            },
            "frames": {
                "x": 1,
                "y": 1
            }
        },
        {
            "pos": {
                "x": 232,
                "y": 0
            },
            "frames": {
                "x": 1,
                "y": 1
            }
        }
    ],
    "internal": false,
    "batched": false
}